synpla_bootstrap-0.1.4.dist-info/RECORD
synpla_bootstrap-0.1.4.dist-info/DESCRIPTION.rst
synpla_bootstrap-0.1.4.dist-info/top_level.txt
synpla_bootstrap-0.1.4.dist-info/METADATA
synpla_bootstrap-0.1.4.dist-info/WHEEL
synpla_bootstrap-0.1.4.dist-info/metadata.json
synpla_bootstrap/__init__.py
synpla_bootstrap/templates/synpla_bootstrap/wtf.html
synpla_bootstrap/templates/synpla_bootstrap/utils.html
synpla_bootstrap/templates/synpla_bootstrap/base.html
synpla_bootstrap/templates/synpla_bootstrap/fixes.html
synpla_bootstrap/templates/synpla_bootstrap/pagination.html
